{"cameraMode":{"drawMode":0,"name":"Shaded","section":"Shading Mode"},"sceneLighting":false,"audioPlay":false,"sceneViewState":{"m_AlwaysRefresh":false,"showFog":true,"showSkybox":false,"showFlares":true,"showImageEffects":true,"showParticleSystems":true,"showVisualEffectGraphs":true,"m_FxEnabled":true},"in2DMode":false,"pivot":{"x":-1.6277353763580323,"y":0.16837331652641297,"z":-1.9649896621704102},"rotation":{"x":0.05061670020222664,"y":0.4327670633792877,"z":-0.023468704894185067,"w":0.8998796939849854},"size":0.0005173205281607807,"orthographic":false}